{"cameraMode":{"drawMode":0,"name":"Shaded","section":"Shading Mode"},"sceneLighting":false,"audioPlay":false,"sceneViewState":{"showFog":true,"showMaterialUpdate":false,"showSkybox":false,"showFlares":true,"showImageEffects":true,"showParticleSystems":true,"showVisualEffectGraphs":true,"m_FxEnabled":true},"in2DMode":false,"pivot":{"x":0.0,"y":14.296382904052735,"z":4.376989364624023},"rotation":{"x":0.28713828325271609,"y":-0.43302029371261599,"z":0.1477617472410202,"w":0.8415898680686951},"size":29.763668060302736,"orthographic":false}